Metadata-Version: 2.1
Name: KkOrthanc
Version: 0.1.4
Summary: My first python repo for kk.
Home-page: https://github.com/iridiumine/KkOrthanc
Author: iridiumine
Author-email: 3179516080@qq.com
License: MIT
Platform: UNKNOWN
Classifier: License :: OSI Approved :: MIT License
Classifier: Programming Language :: Python
Classifier: Programming Language :: Python :: 3
Classifier: Programming Language :: Python :: 3.6
Classifier: Programming Language :: Python :: Implementation :: CPython
Classifier: Programming Language :: Python :: Implementation :: PyPy
Requires-Python: >=3.6.0
